simpel_menus/__init__.py
simpel_menus/admin.py
simpel_menus/apps.py
simpel_menus/models.py
simpel_menus/version.py
simpel_menus/migrations/0001_initial.py
simpel_menus/migrations/0002_remove_menuitem_icon.py
simpel_menus/migrations/__init__.py
simpel_menus/templates/menu.html
simpel_menus/templatetags/__init__.py
simpel_menus/templatetags/simplemenus_tags.py
simpel_menus/wagtail/__init__.py
simpel_menus/wagtail/admin.py
simpel_menus-0.1.dist-info/LICENSE
simpel_menus-0.1.dist-info/METADATA
simpel_menus-0.1.dist-info/WHEEL
simpel_menus-0.1.dist-info/top_level.txt
simpel_menus-0.1.dist-info/RECORD
