Metadata-Version: 2.1
Name: simpel-menus
Version: 0.1
Summary: Simpel Menus, thats it .
Home-page: https://gitlab.com/simpel-projects/simpel-menus
Author: Rizki Sasri Dwitama
Author-email: sasri.works@gmail.com
License: MIT
Project-URL: Documentation, https://gitlab.com/simpel-projects/simpel-menus/-/wikis/
Project-URL: Source, https://gitlab.com/simpel-projects/simpel-menus
Platform: UNKNOWN
Classifier: Environment :: Web Environment
Classifier: Framework :: Django
Classifier: Intended Audience :: Developers
Classifier: License :: OSI Approved :: MIT License
Classifier: Operating System :: OS Independent
Classifier: Programming Language :: Python
Classifier: Programming Language :: Python :: 3
Classifier: Programming Language :: Python :: 3 :: Only
Classifier: Programming Language :: Python :: 3.8
Classifier: Programming Language :: Python :: 3.9
Classifier: Topic :: Internet :: WWW/HTTP
Classifier: Topic :: Internet :: WWW/HTTP :: Dynamic Content
Classifier: Topic :: Internet :: WWW/HTTP :: WSGI
Classifier: Topic :: Software Development :: Libraries :: Python Modules
Classifier: Topic :: Software Development :: Libraries :: Application Frameworks
Requires-Python: >=3.6
License-File: LICENSE
Requires-Dist: django (<4.0,>=3.2.8)
Requires-Dist: django-mptt
